cast_arg/Effort.csv
cast_arg/__init__.py
cast_arg/actionPlan.py
cast_arg/cause.json
cast_arg/config.py
cast_arg/convert.py
cast_arg/main.py
cast_arg/powerpoint.py
cast_arg/restCall.py
cast_arg/stats.py
cast_arg/pages/__init__.py
cast_arg/pages/hl_benchmark.py
cast_arg/pages/hl_cloud.py
cast_arg/pages/hl_cloud_container.py
cast_arg/pages/hl_greenIt.py
cast_arg/pages/hl_report.py
cast_arg/pages/hl_summary.py
cast_arg/pages/hl_summary.save.py
cast_arg/pages/mri_grades.py
cast_arg/pages/mri_overview.py
cast_arg/pages/mri_report.py
cast_arg/pages/mri_sizing.py
cast_arg/pages/mri_strengh_improvement.py
cast_arg/pages/mri_tech_detail_table.py
com.castsoftware.uc.arg-1.7.5.dist-info/METADATA
com.castsoftware.uc.arg-1.7.5.dist-info/WHEEL
com.castsoftware.uc.arg-1.7.5.dist-info/top_level.txt
com.castsoftware.uc.arg-1.7.5.dist-info/RECORD
