Metadata-Version: 2.1
Name: com.castsoftware.uc.arg
Version: 1.7.5
Summary: Assessment Report Generator (ARG)
Home-page: https://github.com/CAST-Extend/com.castsoftware.uc.arg
Author-email: Nevin Kaplan <n.kaplan@castsoftware.com>, DD Assessment Team <Team.ddassessments@castsoftware.com>
Project-URL: Homepage, https://github.com/CAST-Extend/com.castsoftware.uc.arg
Project-URL: documentation, https://github.com/CAST-Extend/com.castsoftware.uc.arg/wiki
Classifier: Programming Language :: Python :: 3
Classifier: License :: OSI Approved :: GNU General Public License v3 (GPLv3)
Classifier: Operating System :: OS Independent
Requires-Python: >=3.6
Requires-Dist: pandas
Requires-Dist: python-pptx==0.6.19
Requires-Dist: com.castsoftware.uc.python.common>=1.1.14
Requires-Dist: IPython
Requires-Dist: requests
Requires-Dist: Jinja2
Requires-Dist: setuptools
Requires-Dist: inflect
